Metadata-Version: 2.1
Name: superdatabase3000
Version: 0.1.0
Summary: An awesome dataset generator!
Home-page: https://github.com/JeanMax/SuperDatabase3000
Author: JeanMax
Author-email: max@rmrf.fr
License: UNKNOWN
Project-URL: Bug Reports, https://github.com/JeanMax/SuperDatabase3000/issues
Project-URL: Source, https://github.com/JeanMax/SuperDatabase3000/
Keywords: super database
Platform: UNKNOWN
Classifier: Development Status :: 3 - Alpha
Classifier: Intended Audience :: Developers
Classifier: Topic :: Software Development :: Build Tools
Classifier: License :: OSI Approved :: MIT License
Classifier: Programming Language :: Python :: 3
Classifier: Programming Language :: Python :: 3.6
Classifier: Programming Language :: Python :: 3.7
Requires-Python: >=3.6, <4
Provides-Extra: dev
